{ "frames": [
   {
    "filename": "trampoline 0.ase",
    "frame": { "x": 0, "y": 0, "w": 56, "h": 8 },
    "rotated": false,
    "trimmed": false,
    "spriteSourceSize": { "x": 0, "y": 0, "w": 56, "h": 8 },
    "sourceSize": { "w": 56, "h": 8 },
    "duration": 100
   },
   {
    "filename": "trampoline 1.ase",
    "frame": { "x": 0, "y": 8, "w": 56, "h": 8 },
    "rotated": false,
    "trimmed": false,
    "spriteSourceSize": { "x": 0, "y": 0, "w": 56, "h": 8 },
    "sourceSize": { "w": 56, "h": 8 },
    "duration": 100
   },
   {
    "filename": "trampoline 2.ase",
    "frame": { "x": 0, "y": 16, "w": 56, "h": 8 },
    "rotated": false,
    "trimmed": false,
    "spriteSourceSize": { "x": 0, "y": 0, "w": 56, "h": 8 },
    "sourceSize": { "w": 56, "h": 8 },
    "duration": 100
   },
   {
    "filename": "trampoline 3.ase",
    "frame": { "x": 0, "y": 24, "w": 56, "h": 8 },
    "rotated": false,
    "trimmed": false,
    "spriteSourceSize": { "x": 0, "y": 0, "w": 56, "h": 8 },
    "sourceSize": { "w": 56, "h": 8 },
    "duration": 100
   },
   {
    "filename": "trampoline 4.ase",
    "frame": { "x": 0, "y": 32, "w": 56, "h": 8 },
    "rotated": false,
    "trimmed": false,
    "spriteSourceSize": { "x": 0, "y": 0, "w": 56, "h": 8 },
    "sourceSize": { "w": 56, "h": 8 },
    "duration": 25
   },
   {
    "filename": "trampoline 5.ase",
    "frame": { "x": 0, "y": 40, "w": 56, "h": 8 },
    "rotated": false,
    "trimmed": false,
    "spriteSourceSize": { "x": 0, "y": 0, "w": 56, "h": 8 },
    "sourceSize": { "w": 56, "h": 8 },
    "duration": 25
   },
   {
    "filename": "trampoline 6.ase",
    "frame": { "x": 0, "y": 48, "w": 56, "h": 8 },
    "rotated": false,
    "trimmed": false,
    "spriteSourceSize": { "x": 0, "y": 0, "w": 56, "h": 8 },
    "sourceSize": { "w": 56, "h": 8 },
    "duration": 50
   },
   {
    "filename": "trampoline 7.ase",
    "frame": { "x": 0, "y": 56, "w": 56, "h": 8 },
    "rotated": false,
    "trimmed": false,
    "spriteSourceSize": { "x": 0, "y": 0, "w": 56, "h": 8 },
    "sourceSize": { "w": 56, "h": 8 },
    "duration": 25
   },
   {
    "filename": "trampoline 8.ase",
    "frame": { "x": 0, "y": 64, "w": 56, "h": 8 },
    "rotated": false,
    "trimmed": false,
    "spriteSourceSize": { "x": 0, "y": 0, "w": 56, "h": 8 },
    "sourceSize": { "w": 56, "h": 8 },
    "duration": 25
   }
 ],
 "meta": {
  "app": "http://www.aseprite.org/",
  "version": "1.2.28-x64",
  "image": "trampoline.png",
  "format": "I8",
  "size": { "w": 56, "h": 72 },
  "scale": "1",
  "frameTags": [
   { "name": "trampoline_still", "from": 0, "to": 0, "direction": "forward" },
   { "name": "trampoline_small", "from": 1, "to": 3, "direction": "forward" },
   { "name": "trampoline_big", "from": 5, "to": 8, "direction": "forward" }
  ],
  "layers": [
   { "name": "Sprite-Sheet", "opacity": 255, "blendMode": "normal" }
  ],
  "slices": [
  ]
 }
}
